setup.py
macroeco_distributions/__init__.py
macroeco_distributions/macroeco_distributions.py
macroeco_distributions/tests_macroeco_distributions.py
macroecotools/__init__.py
macroecotools/macroecotools.py
macroecotools/test_macroecotools.py
macroecotools.egg-info/PKG-INFO
macroecotools.egg-info/SOURCES.txt
macroecotools.egg-info/dependency_links.txt
macroecotools.egg-info/requires.txt
macroecotools.egg-info/top_level.txt