Metadata-Version: 1.1
Name: macroecotools
Version: 0.4.0
Summary: Tools for conducting macroecological analyses
Home-page: https://github.com/weecology/macroecotools
Author: Xiao Xiao, Kate Thibault, David Harris, Elita Baldridge, and Ethan White
Author-email: UNKNOWN
License: MIT
Platform: UNKNOWN
Classifier: Intended Audience :: Science/Research
Classifier: License :: OSI Approved :: MIT License
Classifier: Programming Language :: Python
Classifier: Programming Language :: Python :: 2
